lazyimread/__init__.py
lazyimread/async_utils.py
lazyimread/dimension_utils.py
lazyimread/dummy_data_generator.py
lazyimread/gui_utils.py
lazyimread/lazyimread.py
lazyimread/saving_utils.py
lazyimread-0.1.13.dist-info/METADATA
lazyimread-0.1.13.dist-info/WHEEL
lazyimread-0.1.13.dist-info/licenses/LICENSE
lazyimread-0.1.13.dist-info/RECORD
