Metadata-Version: 2.4
Name: lazyimread
Version: 0.1.13
Summary: A lazy image reading library for various file formats
Project-URL: Homepage, https://github.com/lyehe/lazyimread
Project-URL: Repository, https://github.com/lyehe/lazyimread.git
Author-email: Yehe Liu <yehe@case.edu>
License: CC0 1.0 Universal (CC0 1.0) Public Domain Dedication
License-File: LICENSE
Classifier: Development Status :: 3 - Alpha
Classifier: Intended Audience :: Developers
Classifier: License :: CC0 1.0 Universal (CC0 1.0) Public Domain Dedication
Classifier: Operating System :: OS Independent
Classifier: Programming Language :: Python :: 3
Classifier: Programming Language :: Python :: 3.10
Classifier: Programming Language :: Python :: 3.11
Classifier: Programming Language :: Python :: 3.12
Requires-Python: >=3.10
Requires-Dist: h5py
Requires-Dist: numpy
Requires-Dist: opencv-python
Requires-Dist: pyyaml
Requires-Dist: tifffile
Requires-Dist: xmltodict
Requires-Dist: zarr
Provides-Extra: dev
Requires-Dist: build; extra == 'dev'
Requires-Dist: ipykernel; extra == 'dev'
Requires-Dist: pre-commit; extra == 'dev'
Requires-Dist: pytest; extra == 'dev'
Requires-Dist: pytest-asyncio; extra == 'dev'
Requires-Dist: ruff; extra == 'dev'
Requires-Dist: tox; extra == 'dev'
Requires-Dist: twine; extra == 'dev'
